ADIC/Pipeline/Pip_factorial_assignment.v
module Pipe_Mips32 (clk1, clk2);
  input clk1, clk2; // Two-phase clock
  reg [31:0] PC, IF_ID_IR, IF_ID_NPC;
  reg [31:0] ID_EX_IR, ID_EX_NPC, ID_EX_A, ID_EX_B, ID_EX_Imm;
  reg [2:0] ID_EX_type, EX_MEM_type, MEM_WB_type;
  reg [31:0] EX_MEM_IR, EX_MEM_ALUOut, EX_MEM_B;
  reg EX_MEM_cond;
  reg [31:0] MEM_WB_IR, MEM_WB_ALUOut, MEM_WB_LMD;
  reg [31:0] Reg [0:31]; // Register bank (32 x 32)
  reg [31:0] Mem [0:1023]; // 1024 x 32 memory
  parameter ADD=6'b000000, SUB=6'b000001, AND=6'b000010, OR=6'b000011,
            SLT=6'b000100, MUL=6'b000101, HLT=6'b111111, LW=6'b001000,
            SW=6'b001001, ADDI=6'b001010, SUBI=6'b001011,SLTI=6'b001100,
            BNEQZ=6'b001101, BEQZ=6'b001110;
  parameter RR_ALU=3'b000, RM_ALU=3'b001, LOAD=3'b010, STORE=3'b011,
            BRANCH=3'b100, HALT=3'b101;
  reg HALTED;
  // Set after HLT instruction is completed (in WB stage)
  reg TAKEN_BRANCH;
  // Required to disable instructions after branch
 
 
  always @(posedge clk1) // IF Stage
    if (HALTED == 0)
    begin
      if (((EX_MEM_IR[31:26] == BEQZ) && (EX_MEM_cond == 1)) ||
          ((EX_MEM_IR[31:26] == BNEQZ) && (EX_MEM_cond == 0)))
      begin
        IF_ID_IR <= #2 Mem[EX_MEM_ALUOut];
        TAKEN_BRANCH <= #2 1'b1;
        IF_ID_NPC <= #2 EX_MEM_ALUOut + 1;
        PC <= #2 EX_MEM_ALUOut + 1;
      end
      else
      begin
        IF_ID_IR <= #2 Mem[PC];
        IF_ID_NPC <= #2 PC + 1;
        PC <= #2 PC + 1;
      end
    end
 
  always @(posedge clk2) // ID Stage
    if (HALTED == 0)
    begin
      if (IF_ID_IR[25:21] == 5'b00000)
        ID_EX_A <= 0;
      else
        ID_EX_A <= #2 Reg[IF_ID_IR[25:21]]; // "rs"
      if (IF_ID_IR[20:16] == 5'b00000)
        ID_EX_B <= 0;
      else
        ID_EX_B <= #2 Reg[IF_ID_IR[20:16]]; // "rt"
      ID_EX_NPC <= #2 IF_ID_NPC;
      ID_EX_IR <= #2 IF_ID_IR;
      ID_EX_Imm <= #2 {{16{IF_ID_IR[15]}}, {IF_ID_IR[15:0]}};
      case (IF_ID_IR[31:26])
        ADD,SUB,AND,OR,SLT,MUL:
          ID_EX_type <= #2 RR_ALU;
        ADDI,SUBI,SLTI:
          ID_EX_type <= #2 RM_ALU;
        LW:
          ID_EX_type <= #2 LOAD;
        SW:
          ID_EX_type <= #2 STORE;
        BNEQZ,BEQZ:
          ID_EX_type <= #2 BRANCH;
        HLT:
          ID_EX_type <= #2 HALT;
        default:
          ID_EX_type <= #2 HALT;
        // Invalid opcode
      endcase
    end
 
  always @(posedge clk1) // EX Stage
    if (HALTED == 0)
    begin
      EX_MEM_type <= #2 ID_EX_type;
      EX_MEM_IR <= #2 ID_EX_IR;
      TAKEN_BRANCH <= #2 0;
      case (ID_EX_type)
        RR_ALU:
        begin
          case (ID_EX_IR[31:26]) // "opcode"
            ADD:
              EX_MEM_ALUOut <= #2 ID_EX_A + ID_EX_B;
            SUB:
              EX_MEM_ALUOut <= #2 ID_EX_A - ID_EX_B;
            AND:
              EX_MEM_ALUOut <= #2 ID_EX_A & ID_EX_B;
            OR:
              EX_MEM_ALUOut <= #2 ID_EX_A | ID_EX_B;
            SLT:
              EX_MEM_ALUOut <= #2 ID_EX_A < ID_EX_B;
            MUL:
              EX_MEM_ALUOut <= #2 ID_EX_A * ID_EX_B;
            default:
              EX_MEM_ALUOut <= #2 32'hxxxxxxxx;
          endcase
        end
        RM_ALU:
        begin
          case (ID_EX_IR[31:26]) // "opcode"
            ADDI:
              EX_MEM_ALUOut <= #2 ID_EX_A + ID_EX_Imm;
            SUBI:
              EX_MEM_ALUOut <= #2 ID_EX_A - ID_EX_Imm;
            SLTI:
              EX_MEM_ALUOut <= #2 ID_EX_A < ID_EX_Imm;
            default:
              EX_MEM_ALUOut <= #2 32'hxxxxxxxx;
          endcase
        end
        LOAD, STORE:
        begin
          EX_MEM_ALUOut <= #2 ID_EX_A + ID_EX_Imm;
          EX_MEM_B <= #2 ID_EX_B;
        end
        BRANCH:
        begin
          EX_MEM_ALUOut <= #2 ID_EX_NPC + ID_EX_Imm;
          EX_MEM_cond <= #2 (ID_EX_A == 0);
        end
      endcase
    end
 
 
  always @(posedge clk2) // MEM Stage
    if (HALTED == 0)
    begin
      MEM_WB_type <= EX_MEM_type;
      MEM_WB_IR <= #2 EX_MEM_IR;
      case (EX_MEM_type)
        RR_ALU, RM_ALU:
          MEM_WB_ALUOut <= #2 EX_MEM_ALUOut;
        LOAD:
          MEM_WB_LMD <= #2 Mem[EX_MEM_ALUOut];
        STORE:
          if (TAKEN_BRANCH == 0) // Disable write
            Mem[EX_MEM_ALUOut] <= #2 EX_MEM_B;
      endcase
    end
 
 
  always @(posedge clk1) // WB Stage
  begin
    if (TAKEN_BRANCH == 0) // Disable write if branch taken
    case (MEM_WB_type)
      RR_ALU:
        Reg[MEM_WB_IR[15:11]] <= #2 MEM_WB_ALUOut; // "rd"
      RM_ALU:
        Reg[MEM_WB_IR[20:16]] <= #2 MEM_WB_ALUOut; // "rt"
      LOAD:
        Reg[MEM_WB_IR[20:16]] <= #2 MEM_WB_LMD; // "rt"
      HALT:
        HALTED <= #2 1'b1;
    endcase
  end
endmodule


//Test bench

module test_mips32;
  reg clk1, clk2;
  integer k;
  reg [31:0]out;
  Pipe_Mips32 mips (clk1, clk2);
  initial
  begin
    clk1 = 0;
    clk2 = 0;
    repeat (400) // Generating two-phase clock
    begin
      #5 clk1 = 1;
      #5 clk1 = 0;
      #5 clk2 = 1;
      #5 clk2 = 0;
    end
  end
  initial
  begin
  mips.Mem[198]=0;
    for (k=0; k<31; k=k+1)
      mips.Reg[k] = k;
    mips.Mem[0]=32'h280a00c8;
    mips.Mem[1]=32'h28020001;
    mips.Mem[2]=32'h0ce77800;
    mips.Mem[3]=32'h21430000;
    mips.Mem[4]=32'h0ce77800;
    mips.Mem[5]=32'h14431000;
    mips.Mem[6]=32'h2c630001;
    mips.Mem[7]=32'h0ce77800;
    mips.Mem[8]=32'h3460fffc;
    mips.Mem[9]=32'h2542fffe;
    mips.Mem[10]=32'h0ce77800;
    mips.Mem[11]=32'hfc000000;
    mips.Mem[200]=7;
   mips.HALTED =0;
mips.PC=0;
        mips.TAKEN_BRANCH = 0;
  end
  always @(*)
  begin
  $monitor("Pc=%d R2=%d mem[198]=%d ",mips.PC,mips.Reg[2],mips.Mem[198]); end
endmodule

ADIC/Assignment/mips.vcd
$date
    May 11, 2024  02:01:31
$end
$version
    TOOL:	ncsim(64)	15.20-s086
$end
$timescale
    1 ns
$end

$scope module test_mips32 $end
$var reg       1 !    clk1  $end
$var reg       1 "    clk2  $end
$var integer  32 #    k  $end

$scope module mips $end
$var wire      1 $    clk1  $end
$var wire      1 %    clk2  $end
$var reg      32 &    PC [31:0] $end
$var reg      32 '    IF_ID_IR [31:0] $end
$var reg      32 (    IF_ID_NPC [31:0] $end
$var reg      32 )    ID_EX_IR [31:0] $end
$var reg      32 *    ID_EX_NPC [31:0] $end
$var reg      32 +    ID_EX_A [31:0] $end
$var reg      32 ,    ID_EX_B [31:0] $end
$var reg      32 -    ID_EX_Imm [31:0] $end
$var reg       3 .    ID_EX_type [2:0] $end
$var reg       3 /    EX_MEM_type [2:0] $end
$var reg       3 0    MEM_WB_type [2:0] $end
$var reg      32 1    EX_MEM_IR [31:0] $end
$var reg      32 2    EX_MEM_ALUOut [31:0] $end
$var reg      32 3    EX_MEM_B [31:0] $end
$var reg       1 4    EX_MEM_cond  $end
$var reg      32 5    MEM_WB_IR [31:0] $end
$var reg      32 6    MEM_WB_ALUOut [31:0] $end
$var reg      32 7    MEM_WB_LMD [31:0] $end
$var parameter  6 8    ADD  $end
$var parameter  6 9    SUB  $end
$var parameter  6 :    AND  $end
$var parameter  6 ;    OR  $end
$var parameter  6 <    SLT  $end
$var parameter  6 =    MUL  $end
$var parameter  6 >    HLT  $end
$var parameter  6 ?    LW  $end
$var parameter  6 @    SW  $end
$var parameter  6 A    ADDI  $end
$var parameter  6 B    SUBI  $end
$var parameter  6 C    SLTI  $end
$var parameter  6 D    BNEQZ  $end
$var parameter  6 E    BEQZ  $end
$var parameter  3 F    RR_ALU  $end
$var parameter  3 G    RM_ALU  $end
$var parameter  3 H    LOAD  $end
$var parameter  3 I    STORE  $end
$var parameter  3 J    BRANCH  $end
$var parameter  3 K    HALT  $end
$var reg       1 L    HALTED  $end
$var reg       1 M    TAKEN_BRANCH  $end
$upscope $end

$upscope $end

$enddefinitions $end
$dumpvars
b101 K
b100 J
b11 I
b10 H
b1 G
b0 F
b1110 E
b1101 D
b1100 C
b1011 B
b1010 A
b1001 @
b1000 ?
b111111 >
b101 =
b100 <
b11 ;
b10 :
b1 9
b0 8
0!
0"
b11111 #
0$
0%
b0 &
bx '
bx (
bx )
bx *
bx +
bx ,
bx -
bx .
bx /
bx 0
bx 1
bx 2
bx 3
x4
bx 5
bx 6
bx 7
0L
0M
$end
#5
1!
1$
#7
b101000000010100000000011001000 '
b1 (
b1 &
#10
0!
0$
#15
1"
1%
b0 +
#17
b1010 ,
b1 *
b101000000010100000000011001000 )
b11001000 -
b1 .
#20
0"
0%
#25
1!
1$
#27
b1 /
b101000000010100000000011001000 1
b11001000 2
b101000000000100000000000000001 '
b10 (
b10 &
#30
0!
0$
#35
1"
1%
b1 0
#37
b101000000010100000000011001000 5
b11001000 6
b10 ,
b10 *
b101000000000100000000000000001 )
b1 -
#40
0"
0%
#45
1!
1$
#47
b101000000000100000000000000001 1
b1 2
b1100111001110111100000000000 '
b11 (
b11 &
#50
0!
0$
#55
1"
1%
#57
b101000000000100000000000000001 5
b1 6
b111 +
b111 ,
b11 *
b1100111001110111100000000000 )
b111100000000000 -
b0 .
#60
0"
0%
#65
1!
1$
#67
b0 /
b1100111001110111100000000000 1
b111 2
b100001010000110000000000000000 '
b100 (
b100 &
#70
0!
0$
#75
1"
1%
b0 0
#77
b1100111001110111100000000000 5
b111 6
b11001000 +
b11 ,
b100 *
b100001010000110000000000000000 )
b0 -
b10 .
#80
0"
0%
#85
1!
1$
#87
b10 /
b100001010000110000000000000000 1
b11001000 2
b11 3
b1100111001110111100000000000 '
b101 (
b101 &
#90
0!
0$
#95
1"
1%
b10 0
#97
b100001010000110000000000000000 5
b111 7
b111 +
b111 ,
b101 *
b1100111001110111100000000000 )
b111100000000000 -
b0 .
#100
0"
0%
#105
1!
1$
#107
b0 /
b1100111001110111100000000000 1
b111 2
b10100010000110001000000000000 '
b110 (
b110 &
#110
0!
0$
#115
1"
1%
b0 0
#117
b1100111001110111100000000000 5
b1 +
b110 *
b10100010000110001000000000000 )
b1000000000000 -
#120
0"
0%
#125
1!
1$
#127
b10100010000110001000000000000 1
b101100011000110000000000000001 '
b111 (
b111 &
#130
0!
0$
#135
1"
1%
#137
b10100010000110001000000000000 5
b111 +
b111 *
b101100011000110000000000000001 )
b1 -
b1 .
#140
0"
0%
#145
1!
1$
#147
b1 /
b101100011000110000000000000001 1
b110 2
b1100111001110111100000000000 '
b1000 (
b1000 &
#150
0!
0$
#155
1"
1%
b1 0
#157
b101100011000110000000000000001 5
b110 6
b1000 *
b1100111001110111100000000000 )
b111100000000000 -
b0 .
#160
0"
0%
#165
1!
1$
#167
b0 /
b1100111001110111100000000000 1
b111 2
b110100011000001111111111111100 '
b1001 (
b1001 &
#170
0!
0$
#175
1"
1%
b0 0
b0 ,
#177
b1100111001110111100000000000 5
b111 6
b110 +
b1001 *
b110100011000001111111111111100 )
b11111111111111111111111111111100 -
b100 .
#180
0"
0%
#185
1!
1$
#187
b100 /
b110100011000001111111111111100 1
b101 2
04
b100101010000101111111111111110 '
b1010 (
b1010 &
#190
0!
0$
#195
1"
1%
b100 0
#197
b110100011000001111111111111100 5
b11001000 +
b111 ,
b1010 *
b100101010000101111111111111110 )
b11111111111111111111111111111110 -
b11 .
#200
0"
0%
#205
1!
1$
#207
b11 /
b100101010000101111111111111110 1
b11000110 2
b111 3
b10100010000110001000000000000 '
1M
b110 (
b110 &
#210
0!
0$
#215
1"
1%
b11 0
#217
b100101010000101111111111111110 5
b111 +
b110 ,
b110 *
b10100010000110001000000000000 )
b1000000000000 -
b0 .
#220
0"
0%
#225
1!
1$
#227
b0 /
b10100010000110001000000000000 1
0M
b101010 2
b101100011000110000000000000001 '
b111 (
b111 &
#230
0!
0$
#235
1"
1%
b0 0
#237
b10100010000110001000000000000 5
b101010 6
b110 +
b111 *
b101100011000110000000000000001 )
b1 -
b1 .
#240
0"
0%
#245
1!
1$
#247
b1 /
b101100011000110000000000000001 1
b101 2
b1100111001110111100000000000 '
b1000 (
b1000 &
#250
0!
0$
#255
1"
1%
b1 0
#257
b101100011000110000000000000001 5
b101 6
b111 +
b111 ,
b1000 *
b1100111001110111100000000000 )
b111100000000000 -
b0 .
#260
0"
0%
#265
1!
1$
#267
b0 /
b1100111001110111100000000000 1
b111 2
b110100011000001111111111111100 '
b1001 (
b1001 &
#270
0!
0$
#275
1"
1%
b0 0
b0 ,
#277
b1100111001110111100000000000 5
b111 6
b101 +
b1001 *
b110100011000001111111111111100 )
b11111111111111111111111111111100 -
b100 .
#280
0"
0%
#285
1!
1$
#287
b100 /
b110100011000001111111111111100 1
b101 2
b100101010000101111111111111110 '
b1010 (
b1010 &
#290
0!
0$
#295
1"
1%
b100 0
#297
b110100011000001111111111111100 5
b11001000 +
b101010 ,
b1010 *
b100101010000101111111111111110 )
b11111111111111111111111111111110 -
b11 .
#300
0"
0%
#305
1!
1$
#307
b11 /
b100101010000101111111111111110 1
b11000110 2
b101010 3
b10100010000110001000000000000 '
1M
b110 (
b110 &
#310
0!
0$
#315
1"
1%
b11 0
#317
b100101010000101111111111111110 5
b101010 +
b101 ,
b110 *
b10100010000110001000000000000 )
b1000000000000 -
b0 .
#320
0"
0%
#325
1!
1$
#327
b0 /
b10100010000110001000000000000 1
0M
b11010010 2
b101100011000110000000000000001 '
b111 (
b111 &
#330
0!
0$
#335
1"
1%
b0 0
#337
b10100010000110001000000000000 5
b11010010 6
b101 +
b111 *
b101100011000110000000000000001 )
b1 -
b1 .
#340
0"
0%
#345
1!
1$
#347
b1 /
b101100011000110000000000000001 1
b100 2
b1100111001110111100000000000 '
b1000 (
b1000 &
#350
0!
0$
#355
1"
1%
b1 0
#357
b101100011000110000000000000001 5
b100 6
b111 +
b111 ,
b1000 *
b1100111001110111100000000000 )
b111100000000000 -
b0 .
#360
0"
0%
#365
1!
1$
#367
b0 /
b1100111001110111100000000000 1
b111 2
b110100011000001111111111111100 '
b1001 (
b1001 &
#370
0!
0$
#375
1"
1%
b0 0
b0 ,
#377
b1100111001110111100000000000 5
b111 6
b100 +
b1001 *
b110100011000001111111111111100 )
b11111111111111111111111111111100 -
b100 .
#380
0"
0%
#385
1!
1$
#387
b100 /
b110100011000001111111111111100 1
b101 2
b100101010000101111111111111110 '
b1010 (
b1010 &
#390
0!
0$
#395
1"
1%
b100 0
#397
b110100011000001111111111111100 5
b11001000 +
b11010010 ,
b1010 *
b100101010000101111111111111110 )
b11111111111111111111111111111110 -
b11 .
