ADIC/Pipeline/pipe_3stage.v
module pipe_3stage (F, A, B, C, D, clk);
parameter N = 10;
input [N-1:0] A, B, C, D;
input clk;
output [N-1:0] F;
reg [N-1:0] L12_x1, L12_x2, L12_D, L23_x3, L23_D, L34_F;
assign F = L34_F;
always @(posedge clk) // stage 1 
begin
L12_x1 <= #4 A + B;
L12_x2 <= #4 C - D;
L12_D <= D; 
end

always @(posedge clk) // STAGE 2
begin
L23_x3 <= #4 L12_x1 + L12_x2;
L23_D <= L12_D; 
end

always @(posedge clk) // STAGE 3
L34_F <= #6 L23_x3 * L23_D; 
endmodule




module pipe_3stage_test;
parameter N = 10;
wire [N-1:0] F;
reg [N-1:0] A, B, C, D;
reg clk;
pipe_3stage PIPE1 (F, A, B, C, D, clk);
initial clk = 0;
always #10 clk = ~clk;

initial
begin
#5 A = 11; B = 12; C = 13; D = 3; // F = 99 
#20 A = 10; B = 10; C = 5; D = 10; // F =150
#20 A = 2; B = 2; C = 2; D = 4; // F = 8
#20 A = 15; B = 10; C = 8; D = 2; // F = 62 
#20 A = 8; B = 15; C = 5; D = 0; // F = 0 
#20 A = 10; B = 20; C = 5; D = 3; // F = 66 
#20 A = 10; B = 10; C = 30; D = 1; // F = 49 
#20 A = 30; B = 1; C = 2; D = 4; // F = 116 
end
initial
begin
$dumpfile ("pipe_3stage.vcd");
$dumpvars (0, pipe_3stage_test);
$monitor ($time,":F = %d", F);
#300 $finish;
end
endmodule

ADIC/Pipeline/pipe_3stage.vcd
$date
    May 23, 2024  10:54:51
$end
$version
    TOOL:	ncsim(64)	15.20-s086
$end
$timescale
    1 ns
$end

$scope module pipe_3stage_test $end
$var parameter 32 !    N  $end
$var wire     10 "    F [9:0] $end
$var reg      10 #    A [9:0] $end
$var reg      10 $    B [9:0] $end
$var reg      10 %    C [9:0] $end
$var reg      10 &    D [9:0] $end
$var reg       1 '    clk  $end

$scope module PIPE1 $end
$var parameter 32 (    N  $end
$var wire     10 )    A [9:0] $end
$var wire     10 *    B [9:0] $end
$var wire     10 +    C [9:0] $end
$var wire     10 ,    D [9:0] $end
$var wire      1 -    clk  $end
$var wire     10 "    F [9:0] $end
$var reg      10 .    L12_x1 [9:0] $end
$var reg      10 /    L12_x2 [9:0] $end
$var reg      10 0    L12_D [9:0] $end
$var reg      10 1    L23_x3 [9:0] $end
$var reg      10 2    L23_D [9:0] $end
$var reg      10 3    L34_F [9:0] $end
$upscope $end

$upscope $end

$enddefinitions $end
$dumpvars
b1010 (
b1010 !
bx "
bx #
bx $
bx %
bx &
0'
bx )
bx *
bx +
bx ,
0-
bx .
bx /
bx 0
bx 1
bx 2
bx 3
$end
#5
b1011 #
b1100 $
b1101 %
b11 &
b11 ,
b1101 +
b1100 *
b1011 )
#10
1'
1-
b11 0
#14
b10111 .
b1010 /
#20
0'
0-
#25
b1010 #
b1010 $
b101 %
b1010 &
b1010 ,
b101 +
b1010 *
b1010 )
#30
1'
1-
b11 2
b1010 0
#34
b100001 1
b10100 .
b1111111011 /
#40
0'
0-
#45
b10 #
b10 $
b10 %
b100 &
b100 ,
b10 +
b10 *
b10 )
#50
1'
1-
b1010 2
b100 0
#54
b1111 1
b100 .
b1111111110 /
#56
b1100011 3
b1100011 "
#60
0'
0-
#65
b1111 #
b1010 $
b1000 %
b10 &
b10 ,
b1000 +
b1010 *
b1111 )
#70
1'
1-
b100 2
b10 0
#74
b10 1
b11001 .
b110 /
#76
b10010110 3
b10010110 "
#80
0'
0-
#85
b1000 #
b1111 $
b101 %
b0 &
b0 ,
b101 +
b1111 *
b1000 )
#90
1'
1-
b10 2
b0 0
#94
b11111 1
b10111 .
b101 /
#96
b1000 3
b1000 "
#100
0'
0-
#105
b1010 #
b10100 $
b11 &
b11 ,
b10100 *
b1010 )
#110
1'
1-
b0 2
b11 0
#114
b11100 1
b11110 .
b10 /
#116
b111110 3
b111110 "
#120
0'
0-
#125
b1010 $
b11110 %
b1 &
b1 ,
b11110 +
b1010 *
#130
1'
1-
b11 2
b1 0
#134
b100000 1
b10100 .
b11101 /
#136
b0 3
b0 "
#140
0'
0-
#145
b11110 #
b1 $
b10 %
b100 &
b100 ,
b10 +
b1 *
b11110 )
#150
1'
1-
b1 2
b100 0
#154
b110001 1
b11111 .
b1111111110 /
#156
b1100000 3
b1100000 "
#160
0'
0-
#170
1'
1-
b100 2
#174
b11101 1
#176
b110001 3
b110001 "
#180
0'
0-
#190
1'
1-
#196
b1110100 3
b1110100 "
